pycamps/__init__.py
pycamps/examples/example_1.py
pycamps/examples/example_2.py
pycamps/examples/example_3.py
pycamps/examples/example_4.py
pycamps/examples/parameters/G1.mat
pycamps/examples/parameters/G2.mat
pycamps/examples/parameters/G22.mat
pycamps/examples/parameters/G23.mat
pycamps/examples/parameters/G3.mat
pycamps/examples/parameters/G4.mat
pycamps/examples/parameters/G5.mat
pycamps/examples/parameters/H1.mat
pycamps/examples/parameters/I1.mat
pycamps/examples/parameters/IM14.mat
pycamps/examples/parameters/IM2.mat
pycamps/examples/parameters/L1.mat
pycamps/examples/parameters/L11.mat
pycamps/examples/parameters/L12.mat
pycamps/examples/parameters/L13.mat
pycamps/examples/parameters/L14.mat
pycamps/examples/parameters/L15.mat
pycamps/examples/parameters/L16.mat
pycamps/examples/parameters/L17.mat
pycamps/examples/parameters/L18.mat
pycamps/examples/parameters/L19.mat
pycamps/examples/parameters/L2.mat
pycamps/examples/parameters/L20.mat
pycamps/examples/parameters/L21.mat
pycamps/examples/parameters/L22.mat
pycamps/examples/parameters/L23.mat
pycamps/examples/parameters/PE12.mat
pycamps/examples/parameters/PV21.mat
pycamps/examples/parameters/TL_10_19.mat
pycamps/examples/parameters/TL_10_20.mat
pycamps/examples/parameters/TL_1_2.mat
pycamps/examples/parameters/TL_1_21.mat
pycamps/examples/parameters/TL_1_22.mat
pycamps/examples/parameters/TL_1_23.mat
pycamps/examples/parameters/TL_1_3.mat
pycamps/examples/parameters/TL_1_4.mat
pycamps/examples/parameters/TL_22_21.mat
pycamps/examples/parameters/TL_2_23.mat
pycamps/examples/parameters/TL_2_3.mat
pycamps/examples/parameters/TL_2_4.mat
pycamps/examples/parameters/TL_3_11.mat
pycamps/examples/parameters/TL_3_5.mat
pycamps/examples/parameters/TL_4_6.mat
pycamps/examples/parameters/TL_4_7.mat
pycamps/examples/parameters/TL_5_8.mat
pycamps/examples/parameters/TL_5_9.mat
pycamps/examples/parameters/TL_6_12.mat
pycamps/examples/parameters/TL_6_13.mat
pycamps/examples/parameters/TL_6_14.mat
pycamps-0.0.10.dist-info/LICENSE
pycamps-0.0.10.dist-info/METADATA
pycamps-0.0.10.dist-info/WHEEL
pycamps-0.0.10.dist-info/RECORD
