Metadata-Version: 2.1
Name: PyCAMPS
Version: 0.0.10
Summary: Centralized Automated Modeling of Power Systems in Python
License: CC-BY-NC-4.0
Author: Anish Ravichandran
Author-email: anishrav@mit.edu
Requires-Python: >=3.10,<4.0
Classifier: License :: Other/Proprietary License
Classifier: Programming Language :: Python :: 3
Classifier: Programming Language :: Python :: 3.10
Classifier: Programming Language :: Python :: 3.11
Classifier: Programming Language :: Python :: 3.12
Requires-Dist: matplotlib
Requires-Dist: mpmath
Requires-Dist: numpy
Requires-Dist: pytest
Requires-Dist: scipy
Requires-Dist: sympy
